{"nodes": [{"id": "server_services_tocindexer_js", "label": "tocIndexer.js", "file_type": "code", "source_file": "server\\services\\tocIndexer.js", "source_location": "L1"}, {"id": "tocindexer_isnonvarsityevent", "label": "_isNonVarsityEvent()", "file_type": "code", "source_file": "server\\services\\tocIndexer.js", "source_location": "L22"}, {"id": "tocindexer_canonicalabbrfromtext", "label": "_canonicalAbbrFromText()", "file_type": "code", "source_file": "server\\services\\tocIndexer.js", "source_location": "L38"}, {"id": "tocindexer_canonicalabbr", "label": "_canonicalAbbr()", "file_type": "code", "source_file": "server\\services\\tocIndexer.js", "source_location": "L50"}, {"id": "tocindexer_canonicalfromevent", "label": "_canonicalFromEvent()", "file_type": "code", "source_file": "server\\services\\tocIndexer.js", "source_location": "L53"}, {"id": "tocindexer_runwithconcurrency", "label": "runWithConcurrency()", "file_type": "code", "source_file": "server\\services\\tocIndexer.js", "source_location": "L67"}, {"id": "tocindexer_seedtocindex", "label": "seedTocIndex()", "file_type": "code", "source_file": "server\\services\\tocIndexer.js", "source_location": "L80"}, {"id": "tocindexer_crawltournament", "label": "crawlTournament()", "file_type": "code", "source_file": "server\\services\\tocIndexer.js", "source_location": "L111"}, {"id": "tocindexer_indextournament", "label": "indexTournament()", "file_type": "code", "source_file": "server\\services\\tocIndexer.js", "source_location": "L121"}], "edges": [{"source": "server_services_tocindexer_js", "target": "tocindexer_isnonvarsityevent", "relation": "contains", "confidence": "EXTRACTED", "source_file": "server\\services\\tocIndexer.js", "source_location": "L22", "weight": 1.0}, {"source": "server_services_tocindexer_js", "target": "tocindexer_canonicalabbrfromtext", "relation": "contains", "confidence": "EXTRACTED", "source_file": "server\\services\\tocIndexer.js", "source_location": "L38", "weight": 1.0}, {"source": "server_services_tocindexer_js", "target": "tocindexer_canonicalabbr", "relation": "contains", "confidence": "EXTRACTED", "source_file": "server\\services\\tocIndexer.js", "source_location": "L50", "weight": 1.0}, {"source": "server_services_tocindexer_js", "target": "tocindexer_canonicalfromevent", "relation": "contains", "confidence": "EXTRACTED", "source_file": "server\\services\\tocIndexer.js", "source_location": "L53", "weight": 1.0}, {"source": "server_services_tocindexer_js", "target": "tocindexer_runwithconcurrency", "relation": "contains", "confidence": "EXTRACTED", "source_file": "server\\services\\tocIndexer.js", "source_location": "L67", "weight": 1.0}, {"source": "server_services_tocindexer_js", "target": "tocindexer_seedtocindex", "relation": "contains", "confidence": "EXTRACTED", "source_file": "server\\services\\tocIndexer.js", "source_location": "L80", "weight": 1.0}, {"source": "server_services_tocindexer_js", "target": "tocindexer_crawltournament", "relation": "contains", "confidence": "EXTRACTED", "source_file": "server\\services\\tocIndexer.js", "source_location": "L111", "weight": 1.0}, {"source": "server_services_tocindexer_js", "target": "tocindexer_indextournament", "relation": "contains", "confidence": "EXTRACTED", "source_file": "server\\services\\tocIndexer.js", "source_location": "L121", "weight": 1.0}, {"source": "tocindexer_canonicalabbr", "target": "tocindexer_canonicalabbrfromtext", "relation": "calls", "confidence": "EXTRACTED", "source_file": "server\\services\\tocIndexer.js", "source_location": "L51", "weight": 1.0}, {"source": "tocindexer_canonicalfromevent", "target": "tocindexer_isnonvarsityevent", "relation": "calls", "confidence": "EXTRACTED", "source_file": "server\\services\\tocIndexer.js", "source_location": "L55", "weight": 1.0}, {"source": "tocindexer_canonicalfromevent", "target": "tocindexer_canonicalabbrfromtext", "relation": "calls", "confidence": "EXTRACTED", "source_file": "server\\services\\tocIndexer.js", "source_location": "L56", "weight": 1.0}, {"source": "tocindexer_seedtocindex", "target": "tocindexer_runwithconcurrency", "relation": "calls", "confidence": "EXTRACTED", "source_file": "server\\services\\tocIndexer.js", "source_location": "L89", "weight": 1.0}, {"source": "tocindexer_indextournament", "target": "tocindexer_isnonvarsityevent", "relation": "calls", "confidence": "EXTRACTED", "source_file": "server\\services\\tocIndexer.js", "source_location": "L150", "weight": 1.0}, {"source": "tocindexer_indextournament", "target": "tocindexer_canonicalfromevent", "relation": "calls", "confidence": "EXTRACTED", "source_file": "server\\services\\tocIndexer.js", "source_location": "L151", "weight": 1.0}], "raw_calls": [{"caller_nid": "tocindexer_isnonvarsityevent", "callee": "String", "source_file": "server\\services\\tocIndexer.js", "source_location": "L23"}, {"caller_nid": "tocindexer_isnonvarsityevent", "callee": "toUpperCase", "source_file": "server\\services\\tocIndexer.js", "source_location": "L24"}, {"caller_nid": "tocindexer_isnonvarsityevent", "callee": "String", "source_file": "server\\services\\tocIndexer.js", "source_location": "L24"}, {"caller_nid": "tocindexer_isnonvarsityevent", "callee": "test", "source_file": "server\\services\\tocIndexer.js", "source_location": "L25"}, {"caller_nid": "tocindexer_isnonvarsityevent", "callee": "test", "source_file": "server\\services\\tocIndexer.js", "source_location": "L26"}, {"caller_nid": "tocindexer_isnonvarsityevent", "callee": "has", "source_file": "server\\services\\tocIndexer.js", "source_location": "L27"}, {"caller_nid": "tocindexer_isnonvarsityevent", "callee": "test", "source_file": "server\\services\\tocIndexer.js", "source_location": "L28"}, {"caller_nid": "tocindexer_isnonvarsityevent", "callee": "test", "source_file": "server\\services\\tocIndexer.js", "source_location": "L29"}, {"caller_nid": "tocindexer_isnonvarsityevent", "callee": "test", "source_file": "server\\services\\tocIndexer.js", "source_location": "L30"}, {"caller_nid": "tocindexer_isnonvarsityevent", "callee": "test", "source_file": "server\\services\\tocIndexer.js", "source_location": "L31"}, {"caller_nid": "tocindexer_isnonvarsityevent", "callee": "test", "source_file": "server\\services\\tocIndexer.js", "source_location": "L32"}, {"caller_nid": "tocindexer_isnonvarsityevent", "callee": "test", "source_file": "server\\services\\tocIndexer.js", "source_location": "L33"}, {"caller_nid": "tocindexer_isnonvarsityevent", "callee": "test", "source_file": "server\\services\\tocIndexer.js", "source_location": "L34"}, {"caller_nid": "tocindexer_isnonvarsityevent", "callee": "test", "source_file": "server\\services\\tocIndexer.js", "source_location": "L35"}, {"caller_nid": "tocindexer_canonicalabbrfromtext", "callee": "toUpperCase", "source_file": "server\\services\\tocIndexer.js", "source_location": "L39"}, {"caller_nid": "tocindexer_canonicalabbrfromtext", "callee": "String", "source_file": "server\\services\\tocIndexer.js", "source_location": "L39"}, {"caller_nid": "tocindexer_canonicalabbrfromtext", "callee": "test", "source_file": "server\\services\\tocIndexer.js", "source_location": "L41"}, {"caller_nid": "tocindexer_canonicalabbrfromtext", "callee": "test", "source_file": "server\\services\\tocIndexer.js", "source_location": "L45"}, {"caller_nid": "tocindexer_canonicalabbrfromtext", "callee": "test", "source_file": "server\\services\\tocIndexer.js", "source_location": "L46"}, {"caller_nid": "tocindexer_canonicalabbrfromtext", "callee": "test", "source_file": "server\\services\\tocIndexer.js", "source_location": "L47"}, {"caller_nid": "tocindexer_runwithconcurrency", "callee": "from", "source_file": "server\\services\\tocIndexer.js", "source_location": "L76"}, {"caller_nid": "tocindexer_runwithconcurrency", "callee": "min", "source_file": "server\\services\\tocIndexer.js", "source_location": "L76"}, {"caller_nid": "tocindexer_runwithconcurrency", "callee": "all", "source_file": "server\\services\\tocIndexer.js", "source_location": "L77"}, {"caller_nid": "tocindexer_seedtocindex", "callee": "fetchTocCircuitId", "source_file": "server\\services\\tocIndexer.js", "source_location": "L85"}, {"caller_nid": "tocindexer_seedtocindex", "callee": "fetchCircuitTournIds", "source_file": "server\\services\\tocIndexer.js", "source_location": "L86"}, {"caller_nid": "tocindexer_seedtocindex", "callee": "log", "source_file": "server\\services\\tocIndexer.js", "source_location": "L87"}, {"caller_nid": "tocindexer_seedtocindex", "callee": "listSeasons", "source_file": "server\\services\\tocIndexer.js", "source_location": "L100"}, {"caller_nid": "tocindexer_seedtocindex", "callee": "rebuildSeasonBids", "source_file": "server\\services\\tocIndexer.js", "source_location": "L101"}, {"caller_nid": "tocindexer_seedtocindex", "callee": "recomputeRatings", "source_file": "server\\services\\tocIndexer.js", "source_location": "L102"}, {"caller_nid": "tocindexer_seedtocindex", "callee": "error", "source_file": "server\\services\\tocIndexer.js", "source_location": "L103"}, {"caller_nid": "tocindexer_crawltournament", "callee": "has", "source_file": "server\\services\\tocIndexer.js", "source_location": "L112"}, {"caller_nid": "tocindexer_crawltournament", "callee": "get", "source_file": "server\\services\\tocIndexer.js", "source_location": "L112"}, {"caller_nid": "tocindexer_crawltournament", "callee": "(async () => {\r\n    try { return await indexTournament(tournId); }\r\n    finally { _inflight.delete(tournId); }\r\n  })", "source_file": "server\\services\\tocIndexer.js", "source_location": "L113"}, {"caller_nid": "tocindexer_crawltournament", "callee": "set", "source_file": "server\\services\\tocIndexer.js", "source_location": "L117"}, {"caller_nid": "tocindexer_indextournament", "callee": "fetchTournamentJson", "source_file": "server\\services\\tocIndexer.js", "source_location": "L123"}, {"caller_nid": "tocindexer_indextournament", "callee": "filter", "source_file": "server\\services\\tocIndexer.js", "source_location": "L126"}, {"caller_nid": "tocindexer_indextournament", "callee": "seasonFor", "source_file": "server\\services\\tocIndexer.js", "source_location": "L132"}, {"caller_nid": "tocindexer_indextournament", "callee": "upsertTournament", "source_file": "server\\services\\tocIndexer.js", "source_location": "L133"}, {"caller_nid": "tocindexer_indextournament", "callee": "Number", "source_file": "server\\services\\tocIndexer.js", "source_location": "L134"}, {"caller_nid": "tocindexer_indextournament", "callee": "slice", "source_file": "server\\services\\tocIndexer.js", "source_location": "L140"}, {"caller_nid": "tocindexer_indextournament", "callee": "String", "source_file": "server\\services\\tocIndexer.js", "source_location": "L140"}, {"caller_nid": "tocindexer_indextournament", "callee": "slice", "source_file": "server\\services\\tocIndexer.js", "source_location": "L141"}, {"caller_nid": "tocindexer_indextournament", "callee": "String", "source_file": "server\\services\\tocIndexer.js", "source_location": "L141"}, {"caller_nid": "tocindexer_indextournament", "callee": "clearEventsForTournament", "source_file": "server\\services\\tocIndexer.js", "source_location": "L145"}, {"caller_nid": "tocindexer_indextournament", "callee": "inferBidLevel", "source_file": "server\\services\\tocIndexer.js", "source_location": "L153"}, {"caller_nid": "tocindexer_indextournament", "callee": "upsertEvent", "source_file": "server\\services\\tocIndexer.js", "source_location": "L154"}, {"caller_nid": "tocindexer_indextournament", "callee": "Number", "source_file": "server\\services\\tocIndexer.js", "source_location": "L154"}, {"caller_nid": "tocindexer_indextournament", "callee": "Number", "source_file": "server\\services\\tocIndexer.js", "source_location": "L157"}, {"caller_nid": "tocindexer_indextournament", "callee": "Number", "source_file": "server\\services\\tocIndexer.js", "source_location": "L157"}, {"caller_nid": "tocindexer_indextournament", "callee": "set", "source_file": "server\\services\\tocIndexer.js", "source_location": "L158"}, {"caller_nid": "tocindexer_indextournament", "callee": "Number", "source_file": "server\\services\\tocIndexer.js", "source_location": "L158"}, {"caller_nid": "tocindexer_indextournament", "callee": "parseEarnedBids", "source_file": "server\\services\\tocIndexer.js", "source_location": "L171"}, {"caller_nid": "tocindexer_indextournament", "callee": "set", "source_file": "server\\services\\tocIndexer.js", "source_location": "L172"}, {"caller_nid": "tocindexer_indextournament", "callee": "clearEntriesForTournament", "source_file": "server\\services\\tocIndexer.js", "source_location": "L176"}, {"caller_nid": "tocindexer_indextournament", "callee": "get", "source_file": "server\\services\\tocIndexer.js", "source_location": "L179"}, {"caller_nid": "tocindexer_indextournament", "callee": "Number", "source_file": "server\\services\\tocIndexer.js", "source_location": "L179"}, {"caller_nid": "tocindexer_indextournament", "callee": "teamKeyFor", "source_file": "server\\services\\tocIndexer.js", "source_location": "L181"}, {"caller_nid": "tocindexer_indextournament", "callee": "upsertEntry", "source_file": "server\\services\\tocIndexer.js", "source_location": "L182"}, {"caller_nid": "tocindexer_indextournament", "callee": "Number", "source_file": "server\\services\\tocIndexer.js", "source_location": "L184"}, {"caller_nid": "tocindexer_indextournament", "callee": "Number", "source_file": "server\\services\\tocIndexer.js", "source_location": "L186"}, {"caller_nid": "tocindexer_indextournament", "callee": "get", "source_file": "server\\services\\tocIndexer.js", "source_location": "L190"}, {"caller_nid": "tocindexer_indextournament", "callee": "Number", "source_file": "server\\services\\tocIndexer.js", "source_location": "L190"}, {"caller_nid": "tocindexer_indextournament", "callee": "clearBallotsForTournament", "source_file": "server\\services\\tocIndexer.js", "source_location": "L195"}, {"caller_nid": "tocindexer_indextournament", "callee": "parseBallots", "source_file": "server\\services\\tocIndexer.js", "source_location": "L202"}, {"caller_nid": "tocindexer_indextournament", "callee": "insertBallot", "source_file": "server\\services\\tocIndexer.js", "source_location": "L203"}, {"caller_nid": "tocindexer_indextournament", "callee": "Number", "source_file": "server\\services\\tocIndexer.js", "source_location": "L203"}, {"caller_nid": "tocindexer_indextournament", "callee": "clearResultsForTournament", "source_file": "server\\services\\tocIndexer.js", "source_location": "L208"}, {"caller_nid": "tocindexer_indextournament", "callee": "parseResults", "source_file": "server\\services\\tocIndexer.js", "source_location": "L215"}, {"caller_nid": "tocindexer_indextournament", "callee": "upsertResult", "source_file": "server\\services\\tocIndexer.js", "source_location": "L216"}, {"caller_nid": "tocindexer_indextournament", "callee": "Number", "source_file": "server\\services\\tocIndexer.js", "source_location": "L216"}, {"caller_nid": "tocindexer_indextournament", "callee": "setTournamentCrawled", "source_file": "server\\services\\tocIndexer.js", "source_location": "L221"}, {"caller_nid": "tocindexer_indextournament", "callee": "rebuildSeasonBids", "source_file": "server\\services\\tocIndexer.js", "source_location": "L223"}, {"caller_nid": "tocindexer_indextournament", "callee": "recomputeRatings", "source_file": "server\\services\\tocIndexer.js", "source_location": "L224"}, {"caller_nid": "tocindexer_indextournament", "callee": "error", "source_file": "server\\services\\tocIndexer.js", "source_location": "L225"}]}